{
    "halut_layers": "{\"layer2.0.conv1\": [64, 64, 16]}",
    "layer2.0.conv1.C": 64,
    "layer2.0.conv1.H_size": 11264,
    "layer2.0.conv1.K": 16,
    "layer2.0.conv1.L_size": 524288,
    "layer2.0.conv1.learned_a_shape": [
        200704,
        256
    ],
    "layer2.0.conv1.learned_b_shape": [
        256,
        16
    ],
    "layer2.0.conv1.mae": 0.7553265328979493,
    "layer2.0.conv1.mape": 0.2740665662765503,
    "layer2.0.conv1.mse": 1.0271244147491454,
    "layer2.0.conv1.rows": 64,
    "layer2.0.conv1.scaled_error": 0.019096691081523894,
    "layer2.0.conv1.scaled_shift": 0.00019660940927133198,
    "layer2.0.conv1.stored_array_size": 24,
    "top_1_accuracy": 0.7979599833488464,
    "top_5_accuracy": 0.9484999775886536,
    "total_time": 254.13298640027642
}