{
    "halut_layers": "{\"layer1.2.conv3\": [64, 128, 16]}",
    "layer1.2.conv3.C": 64,
    "layer1.2.conv3.H_size": 11264,
    "layer1.2.conv3.K": 16,
    "layer1.2.conv3.L_size": 1048576,
    "layer1.2.conv3.learned_a_shape": [
        401408,
        64
    ],
    "layer1.2.conv3.learned_b_shape": [
        64,
        16
    ],
    "layer1.2.conv3.mae": 0.03969828014850616,
    "layer1.2.conv3.mape": 0.020385845775604247,
    "layer1.2.conv3.mse": 0.003635717076957226,
    "layer1.2.conv3.rows": 128,
    "layer1.2.conv3.scaled_error": 0.0018152884832024574,
    "layer1.2.conv3.scaled_shift": -0.00012818238913081585,
    "layer1.2.conv3.stored_array_size": 24,
    "top_1_accuracy": 0.8079400062561035,
    "top_5_accuracy": 0.9540999531745911,
    "total_time": 376.8923511747271
}