{
    "halut_layers": "{\"layer3.1.conv2\": [32, 16, 16]}",
    "layer3.1.conv2.C": 32,
    "layer3.1.conv2.H_size": 5632,
    "layer3.1.conv2.K": 16,
    "layer3.1.conv2.L_size": 524288,
    "layer3.1.conv2.learned_a_shape": [
        3136,
        2304
    ],
    "layer3.1.conv2.learned_b_shape": [
        2304,
        256
    ],
    "layer3.1.conv2.learned_d": 2304,
    "layer3.1.conv2.learned_m": 256,
    "layer3.1.conv2.learned_n": 3136,
    "layer3.1.conv2.mae": 1.0352576025390625,
    "layer3.1.conv2.mape": 0.4433747792816162,
    "layer3.1.conv2.mse": 1.8405252293395995,
    "layer3.1.conv2.rows": 16,
    "layer3.1.conv2.scaled_error": 0.0335802823638916,
    "layer3.1.conv2.scaled_shift": 0.0014785159288404975,
    "layer3.1.conv2.stored_array_size": 24,
    "top_1_accuracy": 0.7873599529266357,
    "top_5_accuracy": 0.9436599612236023,
    "total_time": 117.22138985805213
}