{
    "halut_layers": "{\"layer4.0.downsample.0\": [64, -1, 16, 0], \"layer4.0.conv2\": [64, -1, 16, 0], \"layer4.0.conv1\": [64, -1, 16, 0], \"layer3.1.conv2\": [64, -1, 16, 0], \"layer3.1.conv1\": [64, -1, 16, 0], \"layer3.0.downsample.0\": [64, -1, 16, 0], \"layer3.0.conv2\": [64, -1, 16, 0], \"layer3.0.conv1\": [64, -1, 16, 0], \"layer2.1.conv2\": [64, -1, 16, 0], \"layer2.1.conv1\": [64, -1, 16, 0], \"layer2.0.downsample.0\": [64, -1, 16, 0], \"layer2.0.conv2\": [64, -1, 16, 0], \"layer2.0.conv1\": [64, -1, 16, 0], \"layer1.1.conv2\": [64, -1, 16, 0], \"layer1.1.conv1\": [64, -1, 16, 0], \"layer1.0.conv2\": [64, -1, 16, 0], \"layer1.0.conv1\": [64, -1, 16, 0]}",
    "layer1.0.conv1.C": 64,
    "layer1.0.conv1.H_size": 11264,
    "layer1.0.conv1.K": 16,
    "layer1.0.conv1.L_size": 262144,
    "layer1.0.conv1.encoding_algorithm": 0,
    "layer1.0.conv1.learned_a_shape": [
        1,
        261970
    ],
    "layer1.0.conv1.learned_b_shape": [
        261970,
        64
    ],
    "layer1.0.conv1.learned_d": 261970,
    "layer1.0.conv1.learned_m": 64,
    "layer1.0.conv1.learned_n": 1,
    "layer1.0.conv1.mae": 0.2201233591914177,
    "layer1.0.conv1.mape": 0.11508227222561836,
    "layer1.0.conv1.mse": 0.09424720235665639,
    "layer1.0.conv1.rows": -1,
    "layer1.0.conv1.scaled_error": 0.02181480456739664,
    "layer1.0.conv1.scaled_shift": -0.006062678321326773,
    "layer1.0.conv1.stored_array_size": 48,
    "layer1.0.conv2.C": 64,
    "layer1.0.conv2.H_size": 11264,
    "layer1.0.conv2.K": 16,
    "layer1.0.conv2.L_size": 262144,
    "layer1.0.conv2.encoding_algorithm": 0,
    "layer1.0.conv2.learned_a_shape": [
        1,
        261970
    ],
    "layer1.0.conv2.learned_b_shape": [
        261970,
        64
    ],
    "layer1.0.conv2.learned_d": 261970,
    "layer1.0.conv2.learned_m": 64,
    "layer1.0.conv2.learned_n": 1,
    "layer1.0.conv2.mae": 0.057492791223526,
    "layer1.0.conv2.mape": 0.04411077682773272,
    "layer1.0.conv2.mse": 0.006432614228501916,
    "layer1.0.conv2.rows": -1,
    "layer1.0.conv2.scaled_error": 0.012439735450347265,
    "layer1.0.conv2.scaled_shift": -0.001201304472858707,
    "layer1.0.conv2.stored_array_size": 48,
    "layer1.1.conv1.C": 64,
    "layer1.1.conv1.H_size": 11264,
    "layer1.1.conv1.K": 16,
    "layer1.1.conv1.L_size": 262144,
    "layer1.1.conv1.encoding_algorithm": 0,
    "layer1.1.conv1.learned_a_shape": [
        1,
        261970
    ],
    "layer1.1.conv1.learned_b_shape": [
        261970,
        64
    ],
    "layer1.1.conv1.learned_d": 261970,
    "layer1.1.conv1.learned_m": 64,
    "layer1.1.conv1.learned_n": 1,
    "layer1.1.conv1.mae": 0.2664321999867757,
    "layer1.1.conv1.mape": 0.13490581326087317,
    "layer1.1.conv1.mse": 0.1455565771261851,
    "layer1.1.conv1.rows": -1,
    "layer1.1.conv1.scaled_error": 0.01813178301155567,
    "layer1.1.conv1.scaled_shift": -0.0018416133302108695,
    "layer1.1.conv1.stored_array_size": 48,
    "layer1.1.conv2.C": 64,
    "layer1.1.conv2.H_size": 11264,
    "layer1.1.conv2.K": 16,
    "layer1.1.conv2.L_size": 262144,
    "layer1.1.conv2.encoding_algorithm": 0,
    "layer1.1.conv2.learned_a_shape": [
        1,
        261970
    ],
    "layer1.1.conv2.learned_b_shape": [
        261970,
        64
    ],
    "layer1.1.conv2.learned_d": 261970,
    "layer1.1.conv2.learned_m": 64,
    "layer1.1.conv2.learned_n": 1,
    "layer1.1.conv2.mae": 0.07468324429790178,
    "layer1.1.conv2.mape": 0.05765004741748174,
    "layer1.1.conv2.mse": 0.01320019419764479,
    "layer1.1.conv2.rows": -1,
    "layer1.1.conv2.scaled_error": 0.01648832227140665,
    "layer1.1.conv2.scaled_shift": -0.0016998125347308815,
    "layer1.1.conv2.stored_array_size": 48,
    "layer2.0.conv1.C": 64,
    "layer2.0.conv1.H_size": 11264,
    "layer2.0.conv1.K": 16,
    "layer2.0.conv1.L_size": 524288,
    "layer2.0.conv1.encoding_algorithm": 0,
    "layer2.0.conv1.learned_a_shape": [
        1,
        261970
    ],
    "layer2.0.conv1.learned_b_shape": [
        261970,
        128
    ],
    "layer2.0.conv1.learned_d": 261970,
    "layer2.0.conv1.learned_m": 128,
    "layer2.0.conv1.learned_n": 1,
    "layer2.0.conv1.mae": 0.2416920331398646,
    "layer2.0.conv1.mape": 0.13886766799290975,
    "layer2.0.conv1.mse": 0.1153687664270401,
    "layer2.0.conv1.rows": -1,
    "layer2.0.conv1.scaled_error": 0.0182635247250398,
    "layer2.0.conv1.scaled_shift": -0.007093074569726984,
    "layer2.0.conv1.stored_array_size": 48,
    "layer2.0.conv2.C": 64,
    "layer2.0.conv2.H_size": 11264,
    "layer2.0.conv2.K": 16,
    "layer2.0.conv2.L_size": 524288,
    "layer2.0.conv2.encoding_algorithm": 0,
    "layer2.0.conv2.learned_a_shape": [
        1,
        261970
    ],
    "layer2.0.conv2.learned_b_shape": [
        261970,
        128
    ],
    "layer2.0.conv2.learned_d": 261970,
    "layer2.0.conv2.learned_m": 128,
    "layer2.0.conv2.learned_n": 1,
    "layer2.0.conv2.mae": 0.10299993867079417,
    "layer2.0.conv2.mape": 0.07568379626870156,
    "layer2.0.conv2.mse": 0.022772123182813325,
    "layer2.0.conv2.rows": -1,
    "layer2.0.conv2.scaled_error": 0.02011649273534616,
    "layer2.0.conv2.scaled_shift": -0.001029979875200661,
    "layer2.0.conv2.stored_array_size": 48,
    "layer2.0.downsample.0.C": 64,
    "layer2.0.downsample.0.H_size": 11264,
    "layer2.0.downsample.0.K": 16,
    "layer2.0.downsample.0.L_size": 524288,
    "layer2.0.downsample.0.encoding_algorithm": 0,
    "layer2.0.downsample.0.learned_a_shape": [
        1,
        261970
    ],
    "layer2.0.downsample.0.learned_b_shape": [
        261970,
        128
    ],
    "layer2.0.downsample.0.learned_d": 261970,
    "layer2.0.downsample.0.learned_m": 128,
    "layer2.0.downsample.0.learned_n": 1,
    "layer2.0.downsample.0.mae": 0.025714145577450595,
    "layer2.0.downsample.0.mape": 0.017213815669715405,
    "layer2.0.downsample.0.mse": 0.0013418469384312629,
    "layer2.0.downsample.0.rows": -1,
    "layer2.0.downsample.0.scaled_error": 0.004548484463741382,
    "layer2.0.downsample.0.scaled_shift": -0.0001863813477723549,
    "layer2.0.downsample.0.stored_array_size": 48,
    "layer2.1.conv1.C": 64,
    "layer2.1.conv1.H_size": 11264,
    "layer2.1.conv1.K": 16,
    "layer2.1.conv1.L_size": 524288,
    "layer2.1.conv1.encoding_algorithm": 0,
    "layer2.1.conv1.learned_a_shape": [
        1,
        261970
    ],
    "layer2.1.conv1.learned_b_shape": [
        261970,
        128
    ],
    "layer2.1.conv1.learned_d": 261970,
    "layer2.1.conv1.learned_m": 128,
    "layer2.1.conv1.learned_n": 1,
    "layer2.1.conv1.mae": 0.22269549165566763,
    "layer2.1.conv1.mape": 0.13255906068483989,
    "layer2.1.conv1.mse": 0.10811262281139691,
    "layer2.1.conv1.rows": -1,
    "layer2.1.conv1.scaled_error": 0.02030159484942754,
    "layer2.1.conv1.scaled_shift": 0.00045464605259282204,
    "layer2.1.conv1.stored_array_size": 48,
    "layer2.1.conv2.C": 64,
    "layer2.1.conv2.H_size": 11264,
    "layer2.1.conv2.K": 16,
    "layer2.1.conv2.L_size": 524288,
    "layer2.1.conv2.encoding_algorithm": 0,
    "layer2.1.conv2.learned_a_shape": [
        1,
        261970
    ],
    "layer2.1.conv2.learned_b_shape": [
        261970,
        128
    ],
    "layer2.1.conv2.learned_d": 261970,
    "layer2.1.conv2.learned_m": 128,
    "layer2.1.conv2.learned_n": 1,
    "layer2.1.conv2.mae": 0.0954350645740827,
    "layer2.1.conv2.mape": 0.07313494900067648,
    "layer2.1.conv2.mse": 0.016181575788805882,
    "layer2.1.conv2.rows": -1,
    "layer2.1.conv2.scaled_error": 0.035478323399027185,
    "layer2.1.conv2.scaled_shift": -0.0015292092319267492,
    "layer2.1.conv2.stored_array_size": 48,
    "layer3.0.conv1.C": 64,
    "layer3.0.conv1.H_size": 11264,
    "layer3.0.conv1.K": 16,
    "layer3.0.conv1.L_size": 1048576,
    "layer3.0.conv1.encoding_algorithm": 0,
    "layer3.0.conv1.learned_a_shape": [
        1,
        261970
    ],
    "layer3.0.conv1.learned_b_shape": [
        261970,
        256
    ],
    "layer3.0.conv1.learned_d": 261970,
    "layer3.0.conv1.learned_m": 256,
    "layer3.0.conv1.learned_n": 1,
    "layer3.0.conv1.mae": 0.23439514745076498,
    "layer3.0.conv1.mape": 0.14687415214776992,
    "layer3.0.conv1.mse": 0.10154704398711523,
    "layer3.0.conv1.rows": -1,
    "layer3.0.conv1.scaled_error": 0.03218036737044652,
    "layer3.0.conv1.scaled_shift": -0.0015388515277765691,
    "layer3.0.conv1.stored_array_size": 48,
    "layer3.0.conv2.C": 64,
    "layer3.0.conv2.H_size": 11264,
    "layer3.0.conv2.K": 16,
    "layer3.0.conv2.L_size": 1048576,
    "layer3.0.conv2.encoding_algorithm": 0,
    "layer3.0.conv2.learned_a_shape": [
        1,
        261970
    ],
    "layer3.0.conv2.learned_b_shape": [
        261970,
        256
    ],
    "layer3.0.conv2.learned_d": 261970,
    "layer3.0.conv2.learned_m": 256,
    "layer3.0.conv2.learned_n": 1,
    "layer3.0.conv2.mae": 0.16477973591883976,
    "layer3.0.conv2.mape": 0.11792819833755493,
    "layer3.0.conv2.mse": 0.047758161154389384,
    "layer3.0.conv2.rows": -1,
    "layer3.0.conv2.scaled_error": 0.04880842693845431,
    "layer3.0.conv2.scaled_shift": -0.0003804429595494488,
    "layer3.0.conv2.stored_array_size": 48,
    "layer3.0.downsample.0.C": 64,
    "layer3.0.downsample.0.H_size": 11264,
    "layer3.0.downsample.0.K": 16,
    "layer3.0.downsample.0.L_size": 1048576,
    "layer3.0.downsample.0.encoding_algorithm": 0,
    "layer3.0.downsample.0.learned_a_shape": [
        1,
        261970
    ],
    "layer3.0.downsample.0.learned_b_shape": [
        261970,
        256
    ],
    "layer3.0.downsample.0.learned_d": 261970,
    "layer3.0.downsample.0.learned_m": 256,
    "layer3.0.downsample.0.learned_n": 1,
    "layer3.0.downsample.0.mae": 0.03518866870899995,
    "layer3.0.downsample.0.mape": 0.02802690791587035,
    "layer3.0.downsample.0.mse": 0.0021734415277217824,
    "layer3.0.downsample.0.rows": -1,
    "layer3.0.downsample.0.scaled_error": 0.013808037805557252,
    "layer3.0.downsample.0.scaled_shift": 0.0016682421893502275,
    "layer3.0.downsample.0.stored_array_size": 48,
    "layer3.1.conv1.C": 64,
    "layer3.1.conv1.H_size": 11264,
    "layer3.1.conv1.K": 16,
    "layer3.1.conv1.L_size": 1048576,
    "layer3.1.conv1.encoding_algorithm": 0,
    "layer3.1.conv1.learned_a_shape": [
        1,
        261970
    ],
    "layer3.1.conv1.learned_b_shape": [
        261970,
        256
    ],
    "layer3.1.conv1.learned_d": 261970,
    "layer3.1.conv1.learned_m": 256,
    "layer3.1.conv1.learned_n": 1,
    "layer3.1.conv1.mae": 0.29621355431079865,
    "layer3.1.conv1.mape": 0.16867039310932158,
    "layer3.1.conv1.mse": 0.15095042729377747,
    "layer3.1.conv1.rows": -1,
    "layer3.1.conv1.scaled_error": 0.06573908565243085,
    "layer3.1.conv1.scaled_shift": 0.025990574637552104,
    "layer3.1.conv1.stored_array_size": 48,
    "layer3.1.conv2.C": 64,
    "layer3.1.conv2.H_size": 11264,
    "layer3.1.conv2.K": 16,
    "layer3.1.conv2.L_size": 1048576,
    "layer3.1.conv2.encoding_algorithm": 0,
    "layer3.1.conv2.learned_a_shape": [
        1,
        261970
    ],
    "layer3.1.conv2.learned_b_shape": [
        261970,
        256
    ],
    "layer3.1.conv2.learned_d": 261970,
    "layer3.1.conv2.learned_m": 256,
    "layer3.1.conv2.learned_n": 1,
    "layer3.1.conv2.mae": 0.0883342412352562,
    "layer3.1.conv2.mape": 0.07213903803825378,
    "layer3.1.conv2.mse": 0.013184005350867908,
    "layer3.1.conv2.rows": -1,
    "layer3.1.conv2.scaled_error": 0.05830577131509781,
    "layer3.1.conv2.scaled_shift": -0.0015502376200126795,
    "layer3.1.conv2.stored_array_size": 48,
    "layer4.0.conv1.C": 64,
    "layer4.0.conv1.H_size": 11264,
    "layer4.0.conv1.K": 16,
    "layer4.0.conv1.L_size": 2097152,
    "layer4.0.conv1.encoding_algorithm": 0,
    "layer4.0.conv1.learned_a_shape": [
        1,
        261970
    ],
    "layer4.0.conv1.learned_b_shape": [
        261970,
        512
    ],
    "layer4.0.conv1.learned_d": 261970,
    "layer4.0.conv1.learned_m": 512,
    "layer4.0.conv1.learned_n": 1,
    "layer4.0.conv1.mae": 0.21744073138634365,
    "layer4.0.conv1.mape": 0.13901745870510737,
    "layer4.0.conv1.mse": 0.08132818380792936,
    "layer4.0.conv1.rows": -1,
    "layer4.0.conv1.scaled_error": 0.06355378988186518,
    "layer4.0.conv1.scaled_shift": 0.01802152791917324,
    "layer4.0.conv1.stored_array_size": 48,
    "layer4.0.conv2.C": 64,
    "layer4.0.conv2.H_size": 11264,
    "layer4.0.conv2.K": 16,
    "layer4.0.conv2.L_size": 2097152,
    "layer4.0.conv2.encoding_algorithm": 0,
    "layer4.0.conv2.learned_a_shape": [
        1,
        261970
    ],
    "layer4.0.conv2.learned_b_shape": [
        261970,
        512
    ],
    "layer4.0.conv2.learned_d": 261970,
    "layer4.0.conv2.learned_m": 512,
    "layer4.0.conv2.learned_n": 1,
    "layer4.0.conv2.mae": 0.1060691334327062,
    "layer4.0.conv2.mape": 0.08576238745848337,
    "layer4.0.conv2.mse": 0.019255581186215082,
    "layer4.0.conv2.rows": -1,
    "layer4.0.conv2.scaled_error": 0.0686657110730807,
    "layer4.0.conv2.scaled_shift": 0.0009642355208207543,
    "layer4.0.conv2.stored_array_size": 48,
    "layer4.0.downsample.0.C": 64,
    "layer4.0.downsample.0.H_size": 11264,
    "layer4.0.downsample.0.K": 16,
    "layer4.0.downsample.0.L_size": 2097152,
    "layer4.0.downsample.0.encoding_algorithm": 0,
    "layer4.0.downsample.0.learned_a_shape": [
        1,
        261970
    ],
    "layer4.0.downsample.0.learned_b_shape": [
        261970,
        512
    ],
    "layer4.0.downsample.0.learned_d": 261970,
    "layer4.0.downsample.0.learned_m": 512,
    "layer4.0.downsample.0.learned_n": 1,
    "layer4.0.downsample.0.mae": 0.05188861603736877,
    "layer4.0.downsample.0.mape": 0.04249904826879501,
    "layer4.0.downsample.0.mse": 0.004573438918590546,
    "layer4.0.downsample.0.rows": -1,
    "layer4.0.downsample.0.scaled_error": 0.024863055992126466,
    "layer4.0.downsample.0.scaled_shift": 0.002395888589322567,
    "layer4.0.downsample.0.stored_array_size": 48,
    "top_1_accuracy": 76.25,
    "top_5_accuracy": 98.56
}