{
    "halut_layers": "{\"layer3.0.conv2\": [128, -1, 16], \"layer3.0.conv1\": [128, -1, 16], \"layer2.1.conv2\": [64, -1, 16], \"layer2.1.conv1\": [64, -1, 16], \"layer2.0.downsample.0\": [32, -1, 16], \"layer2.0.conv2\": [64, -1, 16], \"layer2.0.conv1\": [64, -1, 16], \"layer1.1.conv2\": [32, -1, 16], \"layer1.1.conv1\": [32, -1, 16], \"layer1.0.conv2\": [32, -1, 16], \"layer1.0.conv1\": [32, -1, 16]}",
    "layer1.0.conv1.C": 32,
    "layer1.0.conv1.H_size": 5632,
    "layer1.0.conv1.K": 16,
    "layer1.0.conv1.L_size": 131072,
    "layer1.0.conv1.learned_a_shape": [
        1,
        261970
    ],
    "layer1.0.conv1.learned_b_shape": [
        261970,
        64
    ],
    "layer1.0.conv1.learned_d": 261970,
    "layer1.0.conv1.learned_m": 64,
    "layer1.0.conv1.learned_n": 1,
    "layer1.0.conv1.mae": 0.4785751700878143,
    "layer1.0.conv1.mape": 0.20519183139801025,
    "layer1.0.conv1.mse": 0.49381029930114745,
    "layer1.0.conv1.rows": -1,
    "layer1.0.conv1.scaled_error": 0.025358959180116655,
    "layer1.0.conv1.scaled_shift": 0.00016018213520292192,
    "layer1.0.conv1.stored_array_size": 48,
    "layer1.0.conv2.C": 32,
    "layer1.0.conv2.H_size": 5632,
    "layer1.0.conv2.K": 16,
    "layer1.0.conv2.L_size": 131072,
    "layer1.0.conv2.learned_a_shape": [
        1,
        261970
    ],
    "layer1.0.conv2.learned_b_shape": [
        261970,
        64
    ],
    "layer1.0.conv2.learned_d": 261970,
    "layer1.0.conv2.learned_m": 64,
    "layer1.0.conv2.learned_n": 1,
    "layer1.0.conv2.mae": 0.2404424337387085,
    "layer1.0.conv2.mape": 0.155980055642128,
    "layer1.0.conv2.mse": 0.10325421345233918,
    "layer1.0.conv2.rows": -1,
    "layer1.0.conv2.scaled_error": 0.034491639906167985,
    "layer1.0.conv2.scaled_shift": -0.003496048891544342,
    "layer1.0.conv2.stored_array_size": 48,
    "layer1.1.conv1.C": 32,
    "layer1.1.conv1.H_size": 5632,
    "layer1.1.conv1.K": 16,
    "layer1.1.conv1.L_size": 131072,
    "layer1.1.conv1.learned_a_shape": [
        1,
        261970
    ],
    "layer1.1.conv1.learned_b_shape": [
        261970,
        64
    ],
    "layer1.1.conv1.learned_d": 261970,
    "layer1.1.conv1.learned_m": 64,
    "layer1.1.conv1.learned_n": 1,
    "layer1.1.conv1.mae": 0.4135361882686615,
    "layer1.1.conv1.mape": 0.2012242600440979,
    "layer1.1.conv1.mse": 0.3281804796695709,
    "layer1.1.conv1.rows": -1,
    "layer1.1.conv1.scaled_error": 0.03300070051550865,
    "layer1.1.conv1.scaled_shift": -0.0007706537229008973,
    "layer1.1.conv1.stored_array_size": 48,
    "layer1.1.conv2.C": 32,
    "layer1.1.conv2.H_size": 5632,
    "layer1.1.conv2.K": 16,
    "layer1.1.conv2.L_size": 131072,
    "layer1.1.conv2.learned_a_shape": [
        1,
        261970
    ],
    "layer1.1.conv2.learned_b_shape": [
        261970,
        64
    ],
    "layer1.1.conv2.learned_d": 261970,
    "layer1.1.conv2.learned_m": 64,
    "layer1.1.conv2.learned_n": 1,
    "layer1.1.conv2.mae": 0.1597869084596634,
    "layer1.1.conv2.mape": 0.11647192590236664,
    "layer1.1.conv2.mse": 0.04353649969100952,
    "layer1.1.conv2.rows": -1,
    "layer1.1.conv2.scaled_error": 0.042435255014896395,
    "layer1.1.conv2.scaled_shift": -0.0016884293675422668,
    "layer1.1.conv2.stored_array_size": 48,
    "layer2.0.conv1.C": 64,
    "layer2.0.conv1.H_size": 11264,
    "layer2.0.conv1.K": 16,
    "layer2.0.conv1.L_size": 524288,
    "layer2.0.conv1.learned_a_shape": [
        1,
        261970
    ],
    "layer2.0.conv1.learned_b_shape": [
        261970,
        128
    ],
    "layer2.0.conv1.learned_d": 261970,
    "layer2.0.conv1.learned_m": 128,
    "layer2.0.conv1.learned_n": 1,
    "layer2.0.conv1.mae": 0.35300817365646364,
    "layer2.0.conv1.mape": 0.17621384828090667,
    "layer2.0.conv1.mse": 0.23260363409519197,
    "layer2.0.conv1.rows": -1,
    "layer2.0.conv1.scaled_error": 0.024539847365021707,
    "layer2.0.conv1.scaled_shift": -0.0017664326127618552,
    "layer2.0.conv1.stored_array_size": 48,
    "layer2.0.conv2.C": 64,
    "layer2.0.conv2.H_size": 11264,
    "layer2.0.conv2.K": 16,
    "layer2.0.conv2.L_size": 524288,
    "layer2.0.conv2.learned_a_shape": [
        1,
        261970
    ],
    "layer2.0.conv2.learned_b_shape": [
        261970,
        128
    ],
    "layer2.0.conv2.learned_d": 261970,
    "layer2.0.conv2.learned_m": 128,
    "layer2.0.conv2.learned_n": 1,
    "layer2.0.conv2.mae": 0.20281634252071382,
    "layer2.0.conv2.mape": 0.13511506474018098,
    "layer2.0.conv2.mse": 0.06972742495536804,
    "layer2.0.conv2.rows": -1,
    "layer2.0.conv2.scaled_error": 0.04916946154236793,
    "layer2.0.conv2.scaled_shift": -0.0001920136357890442,
    "layer2.0.conv2.stored_array_size": 48,
    "layer2.0.downsample.0.C": 32,
    "layer2.0.downsample.0.H_size": 5632,
    "layer2.0.downsample.0.K": 16,
    "layer2.0.downsample.0.L_size": 262144,
    "layer2.0.downsample.0.learned_a_shape": [
        1,
        261970
    ],
    "layer2.0.downsample.0.learned_b_shape": [
        261970,
        128
    ],
    "layer2.0.downsample.0.learned_d": 261970,
    "layer2.0.downsample.0.learned_m": 128,
    "layer2.0.downsample.0.learned_n": 1,
    "layer2.0.downsample.0.mae": 0.06807788734436035,
    "layer2.0.downsample.0.mape": 0.04655576419234276,
    "layer2.0.downsample.0.mse": 0.008442747344076634,
    "layer2.0.downsample.0.rows": -1,
    "layer2.0.downsample.0.scaled_error": 0.013213351485133171,
    "layer2.0.downsample.0.scaled_shift": -0.00013629845064133407,
    "layer2.0.downsample.0.stored_array_size": 48,
    "layer2.1.conv1.C": 64,
    "layer2.1.conv1.H_size": 11264,
    "layer2.1.conv1.K": 16,
    "layer2.1.conv1.L_size": 524288,
    "layer2.1.conv1.learned_a_shape": [
        1,
        261970
    ],
    "layer2.1.conv1.learned_b_shape": [
        261970,
        128
    ],
    "layer2.1.conv1.learned_d": 261970,
    "layer2.1.conv1.learned_m": 128,
    "layer2.1.conv1.learned_n": 1,
    "layer2.1.conv1.mae": 0.364607106590271,
    "layer2.1.conv1.mape": 0.19788533005714418,
    "layer2.1.conv1.mse": 0.2314977858543396,
    "layer2.1.conv1.rows": -1,
    "layer2.1.conv1.scaled_error": 0.04066213072538376,
    "layer2.1.conv1.scaled_shift": 0.003924984852224588,
    "layer2.1.conv1.stored_array_size": 48,
    "layer2.1.conv2.C": 64,
    "layer2.1.conv2.H_size": 11264,
    "layer2.1.conv2.K": 16,
    "layer2.1.conv2.L_size": 524288,
    "layer2.1.conv2.learned_a_shape": [
        1,
        261970
    ],
    "layer2.1.conv2.learned_b_shape": [
        261970,
        128
    ],
    "layer2.1.conv2.learned_d": 261970,
    "layer2.1.conv2.learned_m": 128,
    "layer2.1.conv2.learned_n": 1,
    "layer2.1.conv2.mae": 0.13624773359298706,
    "layer2.1.conv2.mape": 0.10214299877882003,
    "layer2.1.conv2.mse": 0.03031866937279701,
    "layer2.1.conv2.rows": -1,
    "layer2.1.conv2.scaled_error": 0.05683150460720062,
    "layer2.1.conv2.scaled_shift": -0.0018744068555533887,
    "layer2.1.conv2.stored_array_size": 48,
    "layer3.0.conv1.C": 128,
    "layer3.0.conv1.H_size": 22528,
    "layer3.0.conv1.K": 16,
    "layer3.0.conv1.L_size": 2097152,
    "layer3.0.conv1.learned_a_shape": [
        1,
        261970
    ],
    "layer3.0.conv1.learned_b_shape": [
        261970,
        256
    ],
    "layer3.0.conv1.learned_d": 261970,
    "layer3.0.conv1.learned_m": 256,
    "layer3.0.conv1.learned_n": 1,
    "layer3.0.conv1.mae": 0.2534246331214905,
    "layer3.0.conv1.mape": 0.14100845832824707,
    "layer3.0.conv1.mse": 0.10679029924869538,
    "layer3.0.conv1.rows": -1,
    "layer3.0.conv1.scaled_error": 0.0446964586853981,
    "layer3.0.conv1.scaled_shift": 0.006607835455238819,
    "layer3.0.conv1.stored_array_size": 48,
    "layer3.0.conv2.C": 128,
    "layer3.0.conv2.H_size": 22528,
    "layer3.0.conv2.K": 16,
    "layer3.0.conv2.L_size": 2097152,
    "layer3.0.conv2.learned_a_shape": [
        1,
        261970
    ],
    "layer3.0.conv2.learned_b_shape": [
        261970,
        256
    ],
    "layer3.0.conv2.learned_d": 261970,
    "layer3.0.conv2.learned_m": 256,
    "layer3.0.conv2.learned_n": 1,
    "layer3.0.conv2.mae": 0.16540642807483674,
    "layer3.0.conv2.mape": 0.11729236339330673,
    "layer3.0.conv2.mse": 0.04531290200352669,
    "layer3.0.conv2.rows": -1,
    "layer3.0.conv2.scaled_error": 0.06377318404912949,
    "layer3.0.conv2.scaled_shift": 0.006769477923214436,
    "layer3.0.conv2.stored_array_size": 48,
    "top_1_accuracy": 88.21,
    "top_5_accuracy": 99.56
}