{
    "halut_layers": "{\"layer4.2.conv1\": [8, 128, 12, 2]}",
    "layer4.2.conv1.C": 8,
    "layer4.2.conv1.H_size": 4,
    "layer4.2.conv1.K": 12,
    "layer4.2.conv1.L_size": 196608,
    "layer4.2.conv1.encoding_algorithm": 2,
    "layer4.2.conv1.learned_a_shape": [
        6272,
        2048
    ],
    "layer4.2.conv1.learned_b_shape": [
        2048,
        512
    ],
    "layer4.2.conv1.learned_d": 2048,
    "layer4.2.conv1.learned_m": 512,
    "layer4.2.conv1.learned_n": 6272,
    "layer4.2.conv1.mae": 0.970032189025879,
    "layer4.2.conv1.mape": 0.3805764099121094,
    "layer4.2.conv1.mse": 1.787001847229004,
    "layer4.2.conv1.rows": 128,
    "layer4.2.conv1.scaled_error": 0.010000557044744491,
    "layer4.2.conv1.scaled_shift": 0.0024864577649906278,
    "layer4.2.conv1.stored_array_size": 32,
    "top_1_accuracy": 0.7767999768257141,
    "top_5_accuracy": 0.9356600046157837,
    "total_time": 101.47136255074292
}