{
    "halut_layers": "{\"layer4.0.conv2\": [8, 128, 64, 1]}",
    "layer4.0.conv2.C": 8,
    "layer4.0.conv2.H_size": 6144,
    "layer4.0.conv2.K": 64,
    "layer4.0.conv2.L_size": 1048576,
    "layer4.0.conv2.encoding_algorithm": 1,
    "layer4.0.conv2.learned_a_shape": [
        6272,
        4608
    ],
    "layer4.0.conv2.learned_b_shape": [
        4608,
        512
    ],
    "layer4.0.conv2.learned_d": 4608,
    "layer4.0.conv2.learned_m": 512,
    "layer4.0.conv2.learned_n": 6272,
    "layer4.0.conv2.mae": 1.1338326649475097,
    "layer4.0.conv2.mape": 0.4753102507019043,
    "layer4.0.conv2.mse": 2.3186172805786134,
    "layer4.0.conv2.rows": 128,
    "layer4.0.conv2.scaled_error": 0.07186931267738342,
    "layer4.0.conv2.scaled_shift": 0.003852283424397465,
    "layer4.0.conv2.stored_array_size": 32,
    "top_1_accuracy": 0.5712800025939941,
    "top_5_accuracy": 0.8285799622535706,
    "total_time": 96.55189943592995
}