{
    "halut_layers": "{\"layer2.0.conv1\": [16, 2, 12, 1]}",
    "layer2.0.conv1.C": 16,
    "layer2.0.conv1.H_size": 3072,
    "layer2.0.conv1.K": 12,
    "layer2.0.conv1.L_size": 98304,
    "layer2.0.conv1.encoding_algorithm": 1,
    "layer2.0.conv1.learned_a_shape": [
        6272,
        256
    ],
    "layer2.0.conv1.learned_b_shape": [
        256,
        128
    ],
    "layer2.0.conv1.learned_d": 256,
    "layer2.0.conv1.learned_m": 128,
    "layer2.0.conv1.learned_n": 6272,
    "layer2.0.conv1.mae": 1.416578882598877,
    "layer2.0.conv1.mape": 0.4840020896911621,
    "layer2.0.conv1.mse": 3.546138798828125,
    "layer2.0.conv1.rows": 2,
    "layer2.0.conv1.scaled_error": 0.034997457904815676,
    "layer2.0.conv1.scaled_shift": 0.0035318308495730162,
    "layer2.0.conv1.stored_array_size": 32,
    "top_1_accuracy": 0.6979399919509888,
    "top_5_accuracy": 0.8927199840545654,
    "total_time": 161.59373369812965
}