{
    "halut_layers": "{\"layer2.0.conv2\": [16, 2, 4, 2]}",
    "layer2.0.conv2.C": 16,
    "layer2.0.conv2.H_size": 4,
    "layer2.0.conv2.K": 4,
    "layer2.0.conv2.L_size": 32768,
    "layer2.0.conv2.encoding_algorithm": 2,
    "layer2.0.conv2.learned_a_shape": [
        1568,
        1152
    ],
    "layer2.0.conv2.learned_b_shape": [
        1152,
        128
    ],
    "layer2.0.conv2.learned_d": 1152,
    "layer2.0.conv2.learned_m": 128,
    "layer2.0.conv2.learned_n": 1568,
    "layer2.0.conv2.mae": 2.042721086730957,
    "layer2.0.conv2.mape": 0.619400255432129,
    "layer2.0.conv2.mse": 7.420779849853516,
    "layer2.0.conv2.rows": 2,
    "layer2.0.conv2.scaled_error": 0.04566607801437378,
    "layer2.0.conv2.scaled_shift": -0.0008825512596660701,
    "layer2.0.conv2.stored_array_size": 32,
    "top_1_accuracy": 0.6795799732208252,
    "top_5_accuracy": 0.8781999945640564,
    "total_time": 105.55660613626242
}