{
    "halut_layers": "{\"layer2.0.conv2\": [8, 2, 32, 1]}",
    "layer2.0.conv2.C": 8,
    "layer2.0.conv2.H_size": 3072,
    "layer2.0.conv2.K": 32,
    "layer2.0.conv2.L_size": 131072,
    "layer2.0.conv2.encoding_algorithm": 1,
    "layer2.0.conv2.learned_a_shape": [
        1568,
        1152
    ],
    "layer2.0.conv2.learned_b_shape": [
        1152,
        128
    ],
    "layer2.0.conv2.learned_d": 1152,
    "layer2.0.conv2.learned_m": 128,
    "layer2.0.conv2.learned_n": 1568,
    "layer2.0.conv2.mae": 2.2989488873291015,
    "layer2.0.conv2.mape": 0.677632494430542,
    "layer2.0.conv2.mse": 9.544947153320312,
    "layer2.0.conv2.rows": 2,
    "layer2.0.conv2.scaled_error": 0.05138810799121857,
    "layer2.0.conv2.scaled_shift": -0.0012596540731936692,
    "layer2.0.conv2.stored_array_size": 32,
    "top_1_accuracy": 0.5518999695777893,
    "top_5_accuracy": 0.7764599919319153,
    "total_time": 101.43029076419771
}