{
    "halut_layers": "{\"layer2.3.conv3\": [16, 16, 32, 1]}",
    "layer2.3.conv3.C": 16,
    "layer2.3.conv3.H_size": 6144,
    "layer2.3.conv3.K": 32,
    "layer2.3.conv3.L_size": 1048576,
    "layer2.3.conv3.encoding_algorithm": 1,
    "layer2.3.conv3.learned_a_shape": [
        12544,
        128
    ],
    "layer2.3.conv3.learned_b_shape": [
        128,
        512
    ],
    "layer2.3.conv3.learned_d": 128,
    "layer2.3.conv3.learned_m": 512,
    "layer2.3.conv3.learned_n": 12544,
    "layer2.3.conv3.mae": 0.2460484206008911,
    "layer2.3.conv3.mape": 0.14663013957977294,
    "layer2.3.conv3.mse": 0.12348530807495117,
    "layer2.3.conv3.rows": 16,
    "layer2.3.conv3.scaled_error": 0.014728850415945053,
    "layer2.3.conv3.scaled_shift": -3.4337185671902264e-05,
    "layer2.3.conv3.stored_array_size": 32,
    "top_1_accuracy": 0.7981199622154236,
    "top_5_accuracy": 0.9486199617385864,
    "total_time": 160.42973185516894
}