{
    "halut_layers": "{\"layer2.3.conv3\": [64, 8, 24, 2]}",
    "layer2.3.conv3.C": 64,
    "layer2.3.conv3.H_size": 4,
    "layer2.3.conv3.K": 24,
    "layer2.3.conv3.L_size": 3145728,
    "layer2.3.conv3.encoding_algorithm": 2,
    "layer2.3.conv3.learned_a_shape": [
        6272,
        128
    ],
    "layer2.3.conv3.learned_b_shape": [
        128,
        512
    ],
    "layer2.3.conv3.learned_d": 128,
    "layer2.3.conv3.learned_m": 512,
    "layer2.3.conv3.learned_n": 6272,
    "layer2.3.conv3.mae": 0.09843319722175597,
    "layer2.3.conv3.mape": 0.05972848649024964,
    "layer2.3.conv3.mse": 0.019345223412513733,
    "layer2.3.conv3.rows": 8,
    "layer2.3.conv3.scaled_error": 0.005897739441990853,
    "layer2.3.conv3.scaled_shift": 0.0007782743175327778,
    "layer2.3.conv3.stored_array_size": 32,
    "top_1_accuracy": 0.8075399994850159,
    "top_5_accuracy": 0.9538799524307251,
    "total_time": 232.01533938385546
}