{
    "halut_layers": "{\"layer2.3.conv3\": [32, 4, 4, 1]}",
    "layer2.3.conv3.C": 32,
    "layer2.3.conv3.H_size": 1536,
    "layer2.3.conv3.K": 4,
    "layer2.3.conv3.L_size": 262144,
    "layer2.3.conv3.encoding_algorithm": 1,
    "layer2.3.conv3.learned_a_shape": [
        3136,
        128
    ],
    "layer2.3.conv3.learned_b_shape": [
        128,
        512
    ],
    "layer2.3.conv3.learned_d": 128,
    "layer2.3.conv3.learned_m": 512,
    "layer2.3.conv3.learned_n": 3136,
    "layer2.3.conv3.mae": 0.27518708686828613,
    "layer2.3.conv3.mape": 0.1632164645576477,
    "layer2.3.conv3.mse": 0.149210767288208,
    "layer2.3.conv3.rows": 4,
    "layer2.3.conv3.scaled_error": 0.016478691866397856,
    "layer2.3.conv3.scaled_shift": 2.3065393268771003e-05,
    "layer2.3.conv3.stored_array_size": 32,
    "top_1_accuracy": 0.798259973526001,
    "top_5_accuracy": 0.9482199549674988,
    "total_time": 185.35154267121106
}