{
    "halut_layers": "{\"layer1.1.conv3\": [16, 2, 8, 0]}",
    "layer1.1.conv3.C": 16,
    "layer1.1.conv3.H_size": 1344,
    "layer1.1.conv3.K": 8,
    "layer1.1.conv3.L_size": 131072,
    "layer1.1.conv3.encoding_algorithm": 0,
    "layer1.1.conv3.learned_a_shape": [
        6272,
        64
    ],
    "layer1.1.conv3.learned_b_shape": [
        64,
        256
    ],
    "layer1.1.conv3.learned_d": 64,
    "layer1.1.conv3.learned_m": 256,
    "layer1.1.conv3.learned_n": 6272,
    "layer1.1.conv3.mae": 1.327607134399414,
    "layer1.1.conv3.mape": 0.6291085373687744,
    "layer1.1.conv3.mse": 3.155612516479492,
    "layer1.1.conv3.rows": 2,
    "layer1.1.conv3.scaled_error": 0.07779279591560363,
    "layer1.1.conv3.scaled_shift": -0.009547462302446366,
    "layer1.1.conv3.stored_array_size": 32,
    "top_1_accuracy": 0.6177799701690674,
    "top_5_accuracy": 0.8381800055503845,
    "total_time": 246.1337713226676
}