{
    "halut_layers": "{\"layer4.0.conv1\": [32, 128, 32, 0]}",
    "layer4.0.conv1.C": 32,
    "layer4.0.conv1.H_size": 12160,
    "layer4.0.conv1.K": 32,
    "layer4.0.conv1.L_size": 2097152,
    "layer4.0.conv1.encoding_algorithm": 0,
    "layer4.0.conv1.learned_a_shape": [
        25088,
        1024
    ],
    "layer4.0.conv1.learned_b_shape": [
        1024,
        512
    ],
    "layer4.0.conv1.learned_d": 1024,
    "layer4.0.conv1.learned_m": 512,
    "layer4.0.conv1.learned_n": 25088,
    "layer4.0.conv1.mae": 2.6409701287841796,
    "layer4.0.conv1.mape": 1.0552889456176757,
    "layer4.0.conv1.mse": 11.296684523925782,
    "layer4.0.conv1.rows": 128,
    "layer4.0.conv1.scaled_error": 0.1226726672744751,
    "layer4.0.conv1.scaled_shift": -0.0012498309411310765,
    "layer4.0.conv1.stored_array_size": 32,
    "top_1_accuracy": 0.002259999979287386,
    "top_5_accuracy": 0.0177800003439188,
    "total_time": 122.18384052813053
}